tootgroup.py-1.5.data/scripts/tootgroup.py
tootgroup_tools/__init__.py
tootgroup_tools/commandline_arguments.py
tootgroup_tools/configuration_management.py
tootgroup.py-1.5.dist-info/LICENSE
tootgroup.py-1.5.dist-info/METADATA
tootgroup.py-1.5.dist-info/WHEEL
tootgroup.py-1.5.dist-info/top_level.txt
tootgroup.py-1.5.dist-info/RECORD
