Metadata-Version: 2.1
Name: tootgroup.py
Version: 1.5
Summary: Group account features on Mastodon and many other Fediverse platforms 
Author-email: Andreas Schreiner <andreas.schreiner@sonnenmulde.at>
Project-URL: Homepage, https://github.com/oe4dns/tootgroup.py
Keywords: mastodon,pleroma,friendica,gotosocial,toot,group,account,fediverse
Classifier: Environment :: Console
Classifier: Development Status :: 5 - Production/Stable
Classifier: Programming Language :: Python :: 3
Classifier: License :: OSI Approved :: GNU General Public License v3 or later (GPLv3+)
Classifier: Operating System :: OS Independent
Requires-Python: >=3.8
License-File: LICENSE
Requires-Dist: Mastodon.py
Requires-Dist: platformdirs
